ppycron/__init__.py
ppycron/src/__init__.py
ppycron/src/base.py
ppycron/src/unix.py
ppycron/src/windows.py
tests/__init__.py
tests/test_auxiliary_methods.py
tests/test_integration.py
tests/test_unix.py
tests/test_windows.py
ppycron-1.1.0.dist-info/LICENSE
ppycron-1.1.0.dist-info/METADATA
ppycron-1.1.0.dist-info/WHEEL
ppycron-1.1.0.dist-info/top_level.txt
ppycron-1.1.0.dist-info/RECORD
