Metadata-Version: 2.1
Name: ppycron
Version: 1.1.0
Summary: PPyCron is a cross-platform Python library for managing scheduled tasks on Linux (cron) and Windows (Task Scheduler).
Home-page: https://github.com/marciobbj/ppycron
Author: Marcio Bernardes Barbosa Junior
Author-email: marciobernardes@live.com
License: MIT License
Project-URL: Bug Reports, https://github.com/marciobbj/ppycron/issues
Project-URL: Source, https://github.com/marciobbj/ppycron
Project-URL: Documentation, https://github.com/marciobbj/ppycron#readme
Keywords: cron scheduler task windows linux unix cross-platform
Platform: UNKNOWN
Classifier: Development Status :: 4 - Beta
Classifier: Intended Audience :: Developers
Classifier: Intended Audience :: System Administrators
Classifier: License :: OSI Approved :: MIT License
Classifier: Operating System :: OS Independent
Classifier: Programming Language :: Python :: 3
Classifier: Programming Language :: Python :: 3.7
Classifier: Programming Language :: Python :: 3.8
Classifier: Programming Language :: Python :: 3.9
Classifier: Programming Language :: Python :: 3.10
Classifier: Programming Language :: Python :: 3.11
Classifier: Topic :: System :: Systems Administration
Classifier: Topic :: Utilities
Requires-Python: >=3.7
License-File: LICENSE
Requires-Dist: attrs>=21.4.0
Requires-Dist: black>=22.3.0
Requires-Dist: click>=8.1.3
Requires-Dist: iniconfig>=1.1.1
Requires-Dist: mypy-extensions>=0.4.3
Requires-Dist: packaging>=21.3
Requires-Dist: pathspec>=0.9.0
Requires-Dist: platformdirs>=2.5.2
Requires-Dist: pluggy>=1.0.0
Requires-Dist: py>=1.11.0
Requires-Dist: pyparsing>=3.0.8
Requires-Dist: pytest
Requires-Dist: pytest-mock
Requires-Dist: tomli>=2.0.1
Requires-Dist: typing-extensions>=4.2.0
